GaojiBashJiaobenBianchengZhinanRevision10Zhongwenban/README.md
GaojiBashJiaobenBianchengZhinanRevision10Zhongwenban/__init__.py
GaojiBashJiaobenBianchengZhinanRevision10Zhongwenban/__main__.py
GaojiBashJiaobenBianchengZhinanRevision10Zhongwenban/file.epub
GaojiBashJiaobenBianchengZhinanRevision10Zhongwenban/index.html
GaojiBashJiaobenBianchengZhinanRevision10Zhongwenban/css/__init__.py
GaojiBashJiaobenBianchengZhinanRevision10Zhongwenban/css/annotations.css
GaojiBashJiaobenBianchengZhinanRevision10Zhongwenban/css/main.css
GaojiBashJiaobenBianchengZhinanRevision10Zhongwenban/css/normalize.css
GaojiBashJiaobenBianchengZhinanRevision10Zhongwenban/css/popup.css
GaojiBashJiaobenBianchengZhinanRevision10Zhongwenban/font/__init__.py
GaojiBashJiaobenBianchengZhinanRevision10Zhongwenban/font/fontello.eot
GaojiBashJiaobenBianchengZhinanRevision10Zhongwenban/font/fontello.svg
GaojiBashJiaobenBianchengZhinanRevision10Zhongwenban/font/fontello.ttf
GaojiBashJiaobenBianchengZhinanRevision10Zhongwenban/font/fontello.woff
GaojiBashJiaobenBianchengZhinanRevision10Zhongwenban/img/__init__.py
GaojiBashJiaobenBianchengZhinanRevision10Zhongwenban/img/annotator-glyph-sprite.png
GaojiBashJiaobenBianchengZhinanRevision10Zhongwenban/img/annotator-icon-sprite.png
GaojiBashJiaobenBianchengZhinanRevision10Zhongwenban/img/apple-touch-icon.png
GaojiBashJiaobenBianchengZhinanRevision10Zhongwenban/img/cancelfullscreen.png
GaojiBashJiaobenBianchengZhinanRevision10Zhongwenban/img/close.png
GaojiBashJiaobenBianchengZhinanRevision10Zhongwenban/img/fullscreen.png
GaojiBashJiaobenBianchengZhinanRevision10Zhongwenban/img/loader.gif
GaojiBashJiaobenBianchengZhinanRevision10Zhongwenban/img/menu-icon.png
GaojiBashJiaobenBianchengZhinanRevision10Zhongwenban/img/save.png
GaojiBashJiaobenBianchengZhinanRevision10Zhongwenban/img/saved.png
GaojiBashJiaobenBianchengZhinanRevision10Zhongwenban/img/settings-s.png
GaojiBashJiaobenBianchengZhinanRevision10Zhongwenban/img/settings.png
gaoji_bash_jiaoben_biancheng_zhinan_revision_10_zhongwenban-2024.3.3.0.dist-info/METADATA
gaoji_bash_jiaoben_biancheng_zhinan_revision_10_zhongwenban-2024.3.3.0.dist-info/WHEEL
gaoji_bash_jiaoben_biancheng_zhinan_revision_10_zhongwenban-2024.3.3.0.dist-info/entry_points.txt
gaoji_bash_jiaoben_biancheng_zhinan_revision_10_zhongwenban-2024.3.3.0.dist-info/top_level.txt
gaoji_bash_jiaoben_biancheng_zhinan_revision_10_zhongwenban-2024.3.3.0.dist-info/RECORD
